odoo/addons/l10n_ro_account_bank_statement_import_mt940_alpha/README.rst
odoo/addons/l10n_ro_account_bank_statement_import_mt940_alpha/__init__.py
odoo/addons/l10n_ro_account_bank_statement_import_mt940_alpha/__manifest__.py
odoo/addons/l10n_ro_account_bank_statement_import_mt940_alpha/i18n/l10n_ro_account_bank_statement_import_mt940_alpha.pot
odoo/addons/l10n_ro_account_bank_statement_import_mt940_alpha/i18n/ro.po
odoo/addons/l10n_ro_account_bank_statement_import_mt940_alpha/models/__init__.py
odoo/addons/l10n_ro_account_bank_statement_import_mt940_alpha/models/account_bank_statement_import.py
odoo/addons/l10n_ro_account_bank_statement_import_mt940_alpha/models/account_journal.py
odoo/addons/l10n_ro_account_bank_statement_import_mt940_alpha/models/mt940.py
odoo/addons/l10n_ro_account_bank_statement_import_mt940_alpha/readme/CONTRIBUTORS.md
odoo/addons/l10n_ro_account_bank_statement_import_mt940_alpha/readme/DESCRIPTION.md
odoo/addons/l10n_ro_account_bank_statement_import_mt940_alpha/static/description/icon.png
odoo/addons/l10n_ro_account_bank_statement_import_mt940_alpha/static/description/icon.svg
odoo/addons/l10n_ro_account_bank_statement_import_mt940_alpha/static/description/index.html
odoo/addons/l10n_ro_account_bank_statement_import_mt940_alpha/test_files/test_alpha_940.txt
odoo/addons/l10n_ro_account_bank_statement_import_mt940_alpha/tests/__init__.py
odoo/addons/l10n_ro_account_bank_statement_import_mt940_alpha/tests/test_import_bank_statement.py
odoo_addon_l10n_ro_account_bank_statement_import_mt940_alpha-18.0.0.1.0.dist-info/METADATA
odoo_addon_l10n_ro_account_bank_statement_import_mt940_alpha-18.0.0.1.0.dist-info/WHEEL
odoo_addon_l10n_ro_account_bank_statement_import_mt940_alpha-18.0.0.1.0.dist-info/top_level.txt
odoo_addon_l10n_ro_account_bank_statement_import_mt940_alpha-18.0.0.1.0.dist-info/RECORD
